LICENSE
MANIFEST.in
README.md
setup.cfg
setup.py
stride/__init__.py
stride/client.py
stride/collector.py
stride/errors.py
stride/version.py
stride.egg-info/PKG-INFO
stride.egg-info/SOURCES.txt
stride.egg-info/dependency_links.txt
stride.egg-info/requires.txt
stride.egg-info/top_level.txt
stride/test/test_client.py
stride/test/test_collector.py