Metadata-Version: 1.1
Name: stride
Version: 0.1.6
Summary: Python client for Stride
Home-page: https://github.com/pipelinedb/pystride
Author: PipelineDB
Author-email: eng@pipelinedb.com
License: MIT License
Platform: UNKNOWN
Classifier: Development Status :: 4 - Beta
Classifier: Intended Audience :: Developers
Classifier: License :: OSI Approved :: MIT License
Classifier: Operating System :: OS Independent
Classifier: Programming Language :: Python
Classifier: Programming Language :: Python :: 2
Classifier: Programming Language :: Python :: 2.6
Classifier: Programming Language :: Python :: 2.7
